ewokspdf/__init__.py
ewokspdf/tasks/__init__.py
ewokspdf/tasks/average.py
ewokspdf/tasks/config.py
ewokspdf/tasks/constants.py
ewokspdf/tasks/processor.py
ewokspdf/tasks/save_ascii.py
ewokspdf/tasks/save_nexus.py
ewokspdf/tests/__init__.py
ewokspdf/tests/conftest.py
ewokspdf/tests/test_average.py
ewokspdf/tests/test_config.py
ewokspdf/tests/test_processor.py
ewokspdf/tests/test_save_ascii.py
ewokspdf/tests/test_save_nexus.py
ewokspdf/tests/data/__init__.py
ewokspdf/tests/data/average/CeO2_processed.h5
ewokspdf/tests/data/config/config.cfg
ewokspdf/tests/data/processor/CeO2_PDF_processed.h5
ewokspdf/tests/data/processor/background.xy
ewokspdf/tests/data/processor/config.cfg
ewokspdf/tests/data/save/CeO2_PDF_processed.h5
ewokspdf/tests/data/save/background.xy
ewokspdf/tests/data/save/config.cfg
ewokspdf-0.2.0.dist-info/licenses/LICENSE.md
ewokspdf-0.2.0.dist-info/METADATA
ewokspdf-0.2.0.dist-info/WHEEL
ewokspdf-0.2.0.dist-info/entry_points.txt
ewokspdf-0.2.0.dist-info/top_level.txt
ewokspdf-0.2.0.dist-info/RECORD
