Metadata-Version: 2.4
Name: ewokspdf
Version: 0.2.0
Summary: Ewoks project for processing Pair Distribution Function analysis (PDF).
Author-email: ESRF <dau-pydev@esrf.fr>
License: # MIT License
Project-URL: Homepage, https://gitlab.esrf.fr/workflow/ewoksapps/ewokspdf/
Project-URL: Documentation, https://ewokspdf.readthedocs.io/
Project-URL: Repository, https://gitlab.esrf.fr/workflow/ewoksapps/ewokspdf/
Project-URL: Issues, https://gitlab.esrf.fr/workflow/ewoksapps/ewokspdf/issues
Project-URL: Changelog, https://gitlab.esrf.fr/workflow/ewoksapps/ewokspdf/-/blob/main/CHANGELOG.md
Keywords: orange3 add-on,ewoks
Classifier: Intended Audience :: Science/Research
Classifier: License :: OSI Approved :: MIT License
Classifier: Programming Language :: Python :: 3
Classifier: Programming Language :: Python :: 3 :: Only
Classifier: Programming Language :: Python :: 3.11
Classifier: Programming Language :: Python :: 3.12
Classifier: Programming Language :: Python :: 3.13
Requires-Python: >=3.11
License-File: LICENSE.md
Requires-Dist: ewoksxrpd
Provides-Extra: test
Requires-Dist: pytest>=7; extra == "test"
Provides-Extra: dev
Requires-Dist: ewokspdf[test]; extra == "dev"
Requires-Dist: black>=25; extra == "dev"
Requires-Dist: flake8>=4; extra == "dev"
Provides-Extra: doc
Requires-Dist: ewokspdf[test]; extra == "doc"
Requires-Dist: sphinx>=4.5; extra == "doc"
Requires-Dist: sphinx-autodoc-typehints>=1.16; extra == "doc"
Requires-Dist: pydata-sphinx-theme; extra == "doc"
Requires-Dist: myst-parser>=0.18; extra == "doc"
Requires-Dist: sphinx-copybutton; extra == "doc"
Dynamic: license-file
